digGenderExtractor
test
