Metadata-Version: 1.1
Name: digGenderExtractor
Version: 0.2.0
Summary: digGenderExtractor
Home-page: https://github.com/usc-isi-i2/dig-gender-extractor
Author: Lingzhe Teng
Author-email: zwein27@gmail.com
License: UNKNOWN
Download-URL: https://github.com/usc-isi-i2/dig-gender-extractor
Keywords: gender,extractor
Platform: UNKNOWN
